hystfit/__init__.py
hystfit/hystfit.py
hystfit/data/system.ini
hystfit-0.1.dist-info/LICENSE
hystfit-0.1.dist-info/METADATA
hystfit-0.1.dist-info/WHEEL
hystfit-0.1.dist-info/top_level.txt
hystfit-0.1.dist-info/RECORD
